pytest_share_hdf/__init__.py
pytest_share_hdf/plugin.py
pytest_share_hdf-0.1.0.dist-info/LICENSE
pytest_share_hdf-0.1.0.dist-info/METADATA
pytest_share_hdf-0.1.0.dist-info/WHEEL
pytest_share_hdf-0.1.0.dist-info/entry_points.txt
pytest_share_hdf-0.1.0.dist-info/top_level.txt
pytest_share_hdf-0.1.0.dist-info/RECORD
